{
    "all": {
        "pitchers": "5",
        "batters": "10",
        "pitches": "29",
        "max velomax pitch velocity": "97.0",
        "min velomin pitch velocity": "72.7",
        "ff%fourseam fastball %": "51.7",
        "si%sinker %": "13.8",
        "fc%cutter %": "6.9",
        "fs%splitter %": "0.0",
        "ch%changeup %": "17.2",
        "sl%slider %": "6.9",
        "cu%curve %": "3.4",
        "max evmax exit velocity": "108.3",
        "hhhard hit": "4",
        "hh%hard hit %": "66.7",
        "brlbarrels": "0",
        "brl%barrel %": "0.0",
        "ab": "10",
        "avg": ".200",
        "h": "2",
        "1b": "2",
        "2b": "0",
        "3b": "0",
        "hr": "0",
        "so": "1",
        "bipballs in play": "6",
        "liveGames": 5,
        "totGames": 15,
        "updated": "2025-05-28 13:13:15.426107"
    },
    "lad @ cle": [
        {
            "player": "teoscar hernandez",
            "game": "lad @ cle",
            "hr/park": "",
            "pa": "3",
            "dt": "2025-05-28 13:12:48",
            "img": "https://www.mlbstatic.com/team-logos/119.svg",
            "team": "lad",
            "start": "1:10 PM",
            "in": "1",
            "result": "In Progress",
            "evo": "",
            "la": "",
            "dist": ""
        },
        {
            "player": "mookie betts",
            "game": "lad @ cle",
            "hr/park": "",
            "pa": "2",
            "dt": "2025-05-28 13:12:19",
            "img": "https://www.mlbstatic.com/team-logos/119.svg",
            "team": "lad",
            "start": "1:10 PM",
            "in": "1",
            "result": "Flyout",
            "evo": "91.9",
            "la": "45",
            "dist": "291"
        },
        {
            "player": "shohei ohtani",
            "game": "lad @ cle",
            "hr/park": "",
            "pa": "1",
            "dt": "2025-05-28 13:12:19",
            "img": "https://www.mlbstatic.com/team-logos/119.svg",
            "team": "lad",
            "start": "1:10 PM",
            "in": "1",
            "result": "Strikeout",
            "evo": "",
            "la": "",
            "dist": ""
        }
    ],
    "sf @ det": [
        {
            "player": "heliot ramos",
            "game": "sf @ det",
            "hr/park": "",
            "pa": "2",
            "dt": "2025-05-28 13:12:19",
            "img": "https://www.mlbstatic.com/team-logos/137.svg",
            "team": "sf",
            "start": "1:10 PM",
            "in": "1",
            "result": "Batter Timeout",
            "evo": "",
            "la": "",
            "dist": ""
        },
        {
            "player": "mike yastrzemski",
            "game": "sf @ det",
            "hr/park": "0/30",
            "pa": "1",
            "dt": "2025-05-28 13:12:19",
            "img": "https://www.mlbstatic.com/team-logos/137.svg",
            "team": "sf",
            "start": "1:10 PM",
            "in": "1",
            "result": "Flyout",
            "evo": "96.3",
            "la": "41",
            "dist": "326"
        }
    ],
    "min @ tb": [
        {
            "player": "carlos correa",
            "game": "min @ tb",
            "hr/park": "",
            "pa": "3",
            "dt": "2025-05-28 13:13:04",
            "img": "https://www.mlbstatic.com/team-logos/142.svg",
            "team": "min",
            "start": "1:10 PM",
            "in": "1",
            "result": "In Progress",
            "evo": "",
            "la": "",
            "dist": ""
        },
        {
            "player": "ryan jeffers",
            "game": "min @ tb",
            "hr/park": "1/30",
            "pa": "2",
            "dt": "2025-05-28 13:12:19",
            "img": "https://www.mlbstatic.com/team-logos/142.svg",
            "team": "min",
            "start": "1:10 PM",
            "in": "1",
            "result": "Flyout",
            "evo": "95.2",
            "la": "40",
            "dist": "348"
        },
        {
            "player": "trevor larnach",
            "game": "min @ tb",
            "hr/park": "",
            "pa": "1",
            "dt": "2025-05-28 13:12:19",
            "img": "https://www.mlbstatic.com/team-logos/142.svg",
            "team": "min",
            "start": "1:10 PM",
            "in": "1",
            "result": "Single",
            "evo": "108.3",
            "la": "10",
            "dist": "203"
        }
    ],
    "chw @ nym": [
        {
            "player": "chase meidroth",
            "game": "chw @ nym",
            "hr/park": "",
            "pa": "1",
            "dt": "2025-05-28 13:12:19",
            "img": "https://www.mlbstatic.com/team-logos/145.svg",
            "team": "chw",
            "start": "1:10 PM",
            "in": "1",
            "result": "Groundout",
            "evo": "82.6",
            "la": "-20",
            "dist": "7"
        }
    ],
    "bos @ mil": [
        {
            "player": "jarren duran",
            "game": "bos @ mil",
            "hr/park": "",
            "pa": "1",
            "dt": "2025-05-28 13:12:19",
            "img": "https://www.mlbstatic.com/team-logos/111.svg",
            "team": "bos",
            "start": "1:10 PM",
            "in": "1",
            "result": "Single",
            "evo": "102.6",
            "la": "-15",
            "dist": "8"
        }
    ],
    "ath @ hou": [],
    "pit @ ari": [],
    "mia @ sd": [],
    "stl @ bal": [],
    "atl @ phi": [],
    "cin @ kc": [],
    "col @ chc": [],
    "tor @ tex": [],
    "nyy @ laa": [],
    "wsh @ sea": []
}