{
    "all": {
        "pitchers": "2",
        "batters": "16",
        "pitches": "60",
        "max velomax pitch velocity": "95.6",
        "min velomin pitch velocity": "78.2",
        "ff%fourseam fastball %": "38.3",
        "si%sinker %": "15.0",
        "fc%cutter %": "0.0",
        "fs%splitter %": "0.0",
        "ch%changeup %": "8.3",
        "sl%slider %": "1.7",
        "cu%curve %": "36.7",
        "max evmax exit velocity": "104.1",
        "hhhard hit": "5",
        "hh%hard hit %": "33.3",
        "brlbarrels": "0",
        "brl%barrel %": "0.0",
        "ab": "17",
        "avg": ".176",
        "h": "3",
        "1b": "3",
        "2b": "0",
        "3b": "0",
        "hr": "0",
        "so": "2",
        "bipballs in play": "15",
        "liveGames": 1,
        "totGames": 11,
        "updated": "2025-07-10 12:37:47.260225"
    },
    "nym @ bal": [
        {
            "player": "francisco lindor",
            "game": "nym @ bal",
            "hr/park": "",
            "pa": "18",
            "dt": "2025-07-10 12:36:20",
            "img": "https://www.mlbstatic.com/team-logos/121.svg",
            "team": "nym",
            "start": "12:05 PM",
            "in": "3",
            "result": "Single",
            "evo": "96.2",
            "la": "10",
            "dist": "208"
        },
        {
            "player": "brandon nimmo",
            "game": "nym @ bal",
            "hr/park": "0/30",
            "pa": "17",
            "dt": "2025-07-10 12:35:05",
            "img": "https://www.mlbstatic.com/team-logos/121.svg",
            "team": "nym",
            "start": "12:05 PM",
            "in": "3",
            "result": "Flyout",
            "evo": "87.5",
            "la": "36",
            "dist": "325"
        },
        {
            "player": "tyrone taylor",
            "game": "nym @ bal",
            "hr/park": "",
            "pa": "16",
            "dt": "2025-07-10 12:32:35",
            "img": "https://www.mlbstatic.com/team-logos/121.svg",
            "team": "nym",
            "start": "12:05 PM",
            "in": "3",
            "result": "Flyout",
            "evo": "86.0",
            "la": "28",
            "dist": "298"
        },
        {
            "player": "luis vazquez",
            "game": "nym @ bal",
            "hr/park": "",
            "pa": "15",
            "dt": "2025-07-10 12:30:05",
            "img": "https://www.mlbstatic.com/team-logos/110.svg",
            "team": "bal",
            "start": "12:05 PM",
            "in": "2",
            "result": "Groundout",
            "evo": "100.3",
            "la": "-21",
            "dist": "6"
        },
        {
            "player": "colton cowser",
            "game": "nym @ bal",
            "hr/park": "",
            "pa": "14",
            "dt": "2025-07-10 12:30:05",
            "img": "https://www.mlbstatic.com/team-logos/110.svg",
            "team": "bal",
            "start": "12:05 PM",
            "in": "2",
            "result": "Groundout",
            "evo": "104.1",
            "la": "-2",
            "dist": "41"
        },
        {
            "player": "ramon urias",
            "game": "nym @ bal",
            "hr/park": "",
            "pa": "13",
            "dt": "2025-07-10 12:30:05",
            "img": "https://www.mlbstatic.com/team-logos/110.svg",
            "team": "bal",
            "start": "12:05 PM",
            "in": "2",
            "result": "Groundout",
            "evo": "101.0",
            "la": "-5",
            "dist": "25"
        },
        {
            "player": "brett baty",
            "game": "nym @ bal",
            "hr/park": "",
            "pa": "12",
            "dt": "2025-07-10 12:30:05",
            "img": "https://www.mlbstatic.com/team-logos/121.svg",
            "team": "nym",
            "start": "12:05 PM",
            "in": "2",
            "result": "Groundout",
            "evo": "87.4",
            "la": "-36",
            "dist": "4"
        },
        {
            "player": "luis torrens",
            "game": "nym @ bal",
            "hr/park": "",
            "pa": "11",
            "dt": "2025-07-10 12:30:05",
            "img": "https://www.mlbstatic.com/team-logos/121.svg",
            "team": "nym",
            "start": "12:05 PM",
            "in": "2",
            "result": "Groundout",
            "evo": "96.2",
            "la": "6",
            "dist": "116"
        },
        {
            "player": "ronny mauricio",
            "game": "nym @ bal",
            "hr/park": "",
            "pa": "10",
            "dt": "2025-07-10 12:30:05",
            "img": "https://www.mlbstatic.com/team-logos/121.svg",
            "team": "nym",
            "start": "12:05 PM",
            "in": "2",
            "result": "Groundout",
            "evo": "84.0",
            "la": "-20",
            "dist": "8"
        },
        {
            "player": "tyler oneill",
            "game": "nym @ bal",
            "hr/park": "",
            "pa": "9",
            "dt": "2025-07-10 12:30:05",
            "img": "https://www.mlbstatic.com/team-logos/110.svg",
            "team": "bal",
            "start": "12:05 PM",
            "in": "1",
            "result": "Pop Out",
            "evo": "84.7",
            "la": "78",
            "dist": "89"
        },
        {
            "player": "ramon laureano",
            "game": "nym @ bal",
            "hr/park": "0/30",
            "pa": "8",
            "dt": "2025-07-10 12:30:05",
            "img": "https://www.mlbstatic.com/team-logos/110.svg",
            "team": "bal",
            "start": "12:05 PM",
            "in": "1",
            "result": "Lineout",
            "evo": "92.5",
            "la": "24",
            "dist": "326"
        },
        {
            "player": "jordan westburg",
            "game": "nym @ bal",
            "hr/park": "0/30",
            "pa": "7",
            "dt": "2025-07-10 12:30:05",
            "img": "https://www.mlbstatic.com/team-logos/110.svg",
            "team": "bal",
            "start": "12:05 PM",
            "in": "1",
            "result": "Flyout",
            "evo": "83.2",
            "la": "32",
            "dist": "307"
        },
        {
            "player": "jackson holliday",
            "game": "nym @ bal",
            "hr/park": "",
            "pa": "6",
            "dt": "2025-07-10 12:30:05",
            "img": "https://www.mlbstatic.com/team-logos/110.svg",
            "team": "bal",
            "start": "12:05 PM",
            "in": "1",
            "result": "Single",
            "evo": "89.9",
            "la": "17",
            "dist": "237"
        },
        {
            "player": "jesse winker",
            "game": "nym @ bal",
            "hr/park": "",
            "pa": "5",
            "dt": "2025-07-10 12:30:05",
            "img": "https://www.mlbstatic.com/team-logos/121.svg",
            "team": "nym",
            "start": "12:05 PM",
            "in": "1",
            "result": "Pop Out",
            "evo": "87.3",
            "la": "54",
            "dist": "212"
        },
        {
            "player": "pete alonso",
            "game": "nym @ bal",
            "hr/park": "",
            "pa": "4",
            "dt": "2025-07-10 12:30:05",
            "img": "https://www.mlbstatic.com/team-logos/121.svg",
            "team": "nym",
            "start": "12:05 PM",
            "in": "1",
            "result": "Strikeout",
            "evo": "",
            "la": "",
            "dist": ""
        },
        {
            "player": "juan soto",
            "game": "nym @ bal",
            "hr/park": "",
            "pa": "3",
            "dt": "2025-07-10 12:30:05",
            "img": "https://www.mlbstatic.com/team-logos/121.svg",
            "team": "nym",
            "start": "12:05 PM",
            "in": "1",
            "result": "Strikeout",
            "evo": "",
            "la": "",
            "dist": ""
        },
        {
            "player": "francisco lindor",
            "game": "nym @ bal",
            "hr/park": "",
            "pa": "2",
            "dt": "2025-07-10 12:30:05",
            "img": "https://www.mlbstatic.com/team-logos/121.svg",
            "team": "nym",
            "start": "12:05 PM",
            "in": "1",
            "result": "Walk",
            "evo": "",
            "la": "",
            "dist": ""
        },
        {
            "player": "brandon nimmo",
            "game": "nym @ bal",
            "hr/park": "",
            "pa": "1",
            "dt": "2025-07-10 12:30:05",
            "img": "https://www.mlbstatic.com/team-logos/121.svg",
            "team": "nym",
            "start": "12:05 PM",
            "in": "1",
            "result": "Single",
            "evo": "94.0",
            "la": "-15",
            "dist": "12"
        }
    ],
    "nym-gm2 @ bal-gm2": [],
    "chc @ min": [],
    "mia @ cin": [],
    "sea @ nyy": [],
    "tb @ bos": [],
    "cle @ chw": [],
    "wsh @ stl": [],
    "atl @ ath": [],
    "tex @ laa": [],
    "ari @ sd": []
}