{
    "all": {
        "pitchers": "2",
        "batters": "17",
        "pitches": "83",
        "max velomax pitch velocity": "95.7",
        "min velomin pitch velocity": "71.3",
        "ff%fourseam fastball %": "53.0",
        "si%sinker %": "2.4",
        "fc%cutter %": "0.0",
        "fs%splitter %": "0.0",
        "ch%changeup %": "10.8",
        "sl%slider %": "32.5",
        "cu%curve %": "1.2",
        "max evmax exit velocity": "99.3",
        "hhhard hit": "4",
        "hh%hard hit %": "44.4",
        "brlbarrels": "1",
        "brl%barrel %": "11.1",
        "ab": "17",
        "avg": ".118",
        "h": "2",
        "1b": "1",
        "2b": "0",
        "3b": "1",
        "hr": "0",
        "so": "9",
        "bipballs in play": "9",
        "liveGames": 1,
        "totGames": 15,
        "updated": "2025-05-11 12:53:52.284986"
    },
    "mil @ tb": [],
    "chc @ nym": [
        {
            "player": "kyle tucker",
            "game": "chc @ nym",
            "hr/park": "",
            "pa": "19",
            "dt": "2025-05-11 12:53:19",
            "img": "https://www.mlbstatic.com/team-logos/112.svg",
            "team": "chc",
            "start": "12:05 PM",
            "in": "3",
            "result": "Groundout",
            "evo": "97.9",
            "la": "-17",
            "dist": "8"
        },
        {
            "player": "pete crow armstrong",
            "game": "chc @ nym",
            "hr/park": "",
            "pa": "18",
            "dt": "2025-05-11 12:50:49",
            "img": "https://www.mlbstatic.com/team-logos/112.svg",
            "team": "chc",
            "start": "12:05 PM",
            "in": "3",
            "result": "Strikeout",
            "evo": "",
            "la": "",
            "dist": ""
        },
        {
            "player": "jon berti",
            "game": "chc @ nym",
            "hr/park": "",
            "pa": "17",
            "dt": "2025-05-11 12:48:04",
            "img": "https://www.mlbstatic.com/team-logos/112.svg",
            "team": "chc",
            "start": "12:05 PM",
            "in": "3",
            "result": "Flyout",
            "evo": "89.1",
            "la": "44",
            "dist": "273"
        },
        {
            "player": "justin turner",
            "game": "chc @ nym",
            "hr/park": "",
            "pa": "16",
            "dt": "2025-05-11 12:45:03",
            "img": "https://www.mlbstatic.com/team-logos/112.svg",
            "team": "chc",
            "start": "12:05 PM",
            "in": "3",
            "result": "Walk",
            "evo": "",
            "la": "",
            "dist": ""
        },
        {
            "player": "dansby swanson",
            "game": "chc @ nym",
            "hr/park": "",
            "pa": "15",
            "dt": "2025-05-11 12:43:19",
            "img": "https://www.mlbstatic.com/team-logos/112.svg",
            "team": "chc",
            "start": "12:05 PM",
            "in": "3",
            "result": "Single",
            "evo": "93.9",
            "la": "-12",
            "dist": "10"
        },
        {
            "player": "luisangel acuna",
            "game": "chc @ nym",
            "hr/park": "0/30",
            "pa": "14",
            "dt": "2025-05-11 12:39:34",
            "img": "https://www.mlbstatic.com/team-logos/121.svg",
            "team": "nym",
            "start": "12:05 PM",
            "in": "2",
            "result": "Lineout",
            "evo": "96.0",
            "la": "22",
            "dist": "330"
        },
        {
            "player": "luis torrens",
            "game": "chc @ nym",
            "hr/park": "1/30",
            "pa": "13",
            "dt": "2025-05-11 12:35:49",
            "img": "https://www.mlbstatic.com/team-logos/121.svg",
            "team": "nym",
            "start": "12:05 PM",
            "in": "2",
            "result": "Triple",
            "evo": "99.3",
            "la": "31",
            "dist": "378"
        },
        {
            "player": "starling marte",
            "game": "chc @ nym",
            "hr/park": "",
            "pa": "12",
            "dt": "2025-05-11 12:34:34",
            "img": "https://www.mlbstatic.com/team-logos/121.svg",
            "team": "nym",
            "start": "12:05 PM",
            "in": "2",
            "result": "Hit By Pitch",
            "evo": "",
            "la": "",
            "dist": ""
        },
        {
            "player": "brandon nimmo",
            "game": "chc @ nym",
            "hr/park": "",
            "pa": "11",
            "dt": "2025-05-11 12:32:21",
            "img": "https://www.mlbstatic.com/team-logos/121.svg",
            "team": "nym",
            "start": "12:05 PM",
            "in": "2",
            "result": "Strikeout",
            "evo": "",
            "la": "",
            "dist": ""
        },
        {
            "player": "mark vientos",
            "game": "chc @ nym",
            "hr/park": "",
            "pa": "10",
            "dt": "2025-05-11 12:32:04",
            "img": "https://www.mlbstatic.com/team-logos/121.svg",
            "team": "nym",
            "start": "12:05 PM",
            "in": "2",
            "result": "Pop Out",
            "evo": "97.4",
            "la": "64",
            "dist": "165"
        },
        {
            "player": "nico hoerner",
            "game": "chc @ nym",
            "hr/park": "",
            "pa": "9",
            "dt": "2025-05-11 12:27:34",
            "img": "https://www.mlbstatic.com/team-logos/112.svg",
            "team": "chc",
            "start": "12:05 PM",
            "in": "2",
            "result": "Pop Out",
            "evo": "79.4",
            "la": "75",
            "dist": "35"
        },
        {
            "player": "carson kelly",
            "game": "chc @ nym",
            "hr/park": "",
            "pa": "8",
            "dt": "2025-05-11 12:25:06",
            "img": "https://www.mlbstatic.com/team-logos/112.svg",
            "team": "chc",
            "start": "12:05 PM",
            "in": "2",
            "result": "Strikeout",
            "evo": "",
            "la": "",
            "dist": ""
        },
        {
            "player": "michael busch",
            "game": "chc @ nym",
            "hr/park": "",
            "pa": "7",
            "dt": "2025-05-11 12:23:48",
            "img": "https://www.mlbstatic.com/team-logos/112.svg",
            "team": "chc",
            "start": "12:05 PM",
            "in": "2",
            "result": "Flyout",
            "evo": "92.4",
            "la": "51",
            "dist": "254"
        },
        {
            "player": "pete alonso",
            "game": "chc @ nym",
            "hr/park": "",
            "pa": "6",
            "dt": "2025-05-11 12:23:34",
            "img": "https://www.mlbstatic.com/team-logos/121.svg",
            "team": "nym",
            "start": "12:05 PM",
            "in": "1",
            "result": "Strikeout",
            "evo": "",
            "la": "",
            "dist": ""
        },
        {
            "player": "juan soto",
            "game": "chc @ nym",
            "hr/park": "",
            "pa": "5",
            "dt": "2025-05-11 12:23:34",
            "img": "https://www.mlbstatic.com/team-logos/121.svg",
            "team": "nym",
            "start": "12:05 PM",
            "in": "1",
            "result": "Strikeout",
            "evo": "",
            "la": "",
            "dist": ""
        },
        {
            "player": "francisco lindor",
            "game": "chc @ nym",
            "hr/park": "",
            "pa": "4",
            "dt": "2025-05-11 12:23:34",
            "img": "https://www.mlbstatic.com/team-logos/121.svg",
            "team": "nym",
            "start": "12:05 PM",
            "in": "1",
            "result": "Strikeout",
            "evo": "",
            "la": "",
            "dist": ""
        },
        {
            "player": "seiya suzuki",
            "game": "chc @ nym",
            "hr/park": "",
            "pa": "3",
            "dt": "2025-05-11 12:23:34",
            "img": "https://www.mlbstatic.com/team-logos/112.svg",
            "team": "chc",
            "start": "12:05 PM",
            "in": "1",
            "result": "Strikeout",
            "evo": "",
            "la": "",
            "dist": ""
        },
        {
            "player": "kyle tucker",
            "game": "chc @ nym",
            "hr/park": "",
            "pa": "2",
            "dt": "2025-05-11 12:23:34",
            "img": "https://www.mlbstatic.com/team-logos/112.svg",
            "team": "chc",
            "start": "12:05 PM",
            "in": "1",
            "result": "Strikeout",
            "evo": "",
            "la": "",
            "dist": ""
        },
        {
            "player": "pete crow armstrong",
            "game": "chc @ nym",
            "hr/park": "",
            "pa": "1",
            "dt": "2025-05-11 12:23:34",
            "img": "https://www.mlbstatic.com/team-logos/112.svg",
            "team": "chc",
            "start": "12:05 PM",
            "in": "1",
            "result": "Strikeout",
            "evo": "",
            "la": "",
            "dist": ""
        }
    ],
    "stl @ wsh": [],
    "atl @ pit": [],
    "tex @ det": [],
    "cin @ hou": [],
    "bos @ kc": [],
    "sf @ min": [],
    "mia @ chw": [],
    "sd @ col": [],
    "nyy @ ath": [],
    "bal @ laa": [],
    "lad @ ari": [],
    "tor @ sea": [],
    "phi @ cle": []
}